token_fuzz_rs/__init__.py
token_fuzz_rs/__init__.pyi
token_fuzz_rs/py.typed
token_fuzz_rs/token_fuzz_rs.cpython-311-x86_64-linux-musl.so
token_fuzz_rs-0.2.0.dist-info/METADATA
token_fuzz_rs-0.2.0.dist-info/WHEEL
token_fuzz_rs-0.2.0.dist-info/licenses/LICENSE
token_fuzz_rs.libs/libgcc_s-f685abf1.so.1
token_fuzz_rs-0.2.0.dist-info/RECORD
