Metadata-Version: 2.4
Name: token_fuzz_rs
Version: 0.2.0
Classifier: Development Status :: 5 - Production/Stable
Classifier: Intended Audience :: Developers
Classifier: License :: OSI Approved :: MIT License
Classifier: Programming Language :: Python
Classifier: Programming Language :: Python :: 3
Classifier: Programming Language :: Python :: 3 :: Only
Classifier: Programming Language :: Python :: 3.8
Classifier: Programming Language :: Python :: 3.9
Classifier: Programming Language :: Python :: 3.10
Classifier: Programming Language :: Python :: 3.11
Classifier: Programming Language :: Python :: 3.12
Classifier: Programming Language :: Python :: 3.13
Classifier: Programming Language :: Python :: 3.14
Classifier: Programming Language :: Rust
Classifier: Programming Language :: Python :: Implementation :: CPython
Classifier: Programming Language :: Python :: Implementation :: PyPy
Classifier: Topic :: Software Development :: Libraries
Classifier: Topic :: Text Processing
License-File: LICENSE
Summary: Fast token-based fuzzy string matching for very large, static corpora (Rust-backed, Python-first).
Keywords: fuzzy,string matching,similarity,minhash,tokens,rust,pyo3
Author-email: Matthew Akram <mazfh85246@gmail.com>
Requires-Python: >=3.8
Project-URL: Documentation, https://github.com/matthewakram/token_fuzz_rs#readme
Project-URL: Homepage, https://github.com/matthewakram/token_fuzz_rs
Project-URL: Issues, https://github.com/matthewakram/token_fuzz_rs/issues
Project-URL: Repository, https://github.com/matthewakram/token_fuzz_rs
